{
    "(255, 0, 255)": "A Site",
    "(255, 255, 0)": "A Maze",
    "(255, 165, 0)": "A 410",
    "(240, 230, 140)": "A Generator",
    "(0, 100, 0)": "A Default",
    "(176, 224, 230)": "A Dice",
    "(75, 0, 130)": "A Top Site",
    "(245, 245, 220)": "A Rafters/Hell",
    "(139, 69, 19)": "A Screens",
    "(255, 228, 225)": "A Ramp",
    "(230, 230, 250)": "CT Spawn",
    "(112, 128, 144)": "Mid Pallet",
    "(240, 255, 240)": "Mid Boiler",
    "(210, 180, 140)": "Kitchen",
    "(245, 222, 179)": "Tube",
    "(255, 160, 122)": "B Snow Pile Boxes",
    "(255, 215, 0)": "B Hall",
    "(245, 255, 250)": "B Bridge",
    "(173, 255, 47)": "B Orange",
    "(70, 130, 180)": "B Hut",
    "(128, 0, 128)": "B Back",
    "(255, 192, 203)": "B Snowman",
    "(210, 105, 30)": "B Site",
    "(255, 99, 71)": "B Top Site",
    "(218, 165, 32)": "B Default",
    "(50, 205, 50)": "B Danger",
    "(0, 128, 128)": "B Yellow",
    "(255, 105, 180)": "B Cubby",
    "(221, 160, 221)": "B Main",
    "(0, 191, 255)": "B Garage",
    "(0, 0, 255)": "Below Mid Boiler",
    "(188, 143, 143)": "Mid",
    "(0, 255, 0)": "A Slant",
    "(0, 255, 255)": "A Orb",
    "(128, 0, 0)": "A Pipes",
    "(255, 69, 0)": "A Belt",
    "(0, 250, 154)": "A Gate",
    "(255, 20, 147)": "A Nest",
    "(128, 128, 0)": "A Jump Up",
    "(0, 0, 139)": "A Main",
    "(238, 130, 238)": "T Spawn",
    "(0, 206, 209)": "B Snow Pile"
}